{
    "countries": [
        {
            "country": "Kenya",
            "president": "Uhuru Kenyatta",
            "acting_president": false,
            "currency": "kenya snshillings",
            "where": "east africa"
        },
        {
            "country": "Tanzania",
            "president": "Suluhu Hassan",
            "acting_president": true,
            "currency": "kenya snshillings",
            "where": "east africa"
        },
        {
            "country": "Uganda",
            "president": "Yaweri Museveni",
            "acting_president": false,
            "currency": "Uganda shillings",
            "where": "east africa"
        },
        {
            "country": "somali",
            "president": "Hassan Muhamud",
            "acting_president": false,
            "currency": "somali shillings",
            "where": "east africa"
        },
        {
            "country": "Zambia",
            "president": "Hakainde Hichilema",
            "acting_president": false,
            "currency": "zambian kwacha",
            "where": "south central"
        }
    ]
}
